setup.py
Artisan.egg-info/PKG-INFO
Artisan.egg-info/SOURCES.txt
Artisan.egg-info/dependency_links.txt
Artisan.egg-info/not-zip-safe
Artisan.egg-info/top_level.txt
artisan/__init__.py
artisan/commands.py
artisan/controllers.py
artisan/database.py
artisan/helpers.py
artisan/routes.py