Metadata-Version: 1.0
Name: Artisan
Version: 0.0.0
Summary: Coming soon
Home-page: UNKNOWN
Author: Ravindra Marella
Author-email: mv.ravindra007@gmail.com
License: MIT
Platform: UNKNOWN
